nwastdlib/__init__.py
nwastdlib/asyncio.py
nwastdlib/asyncio_cache.py
nwastdlib/debugging.py
nwastdlib/ex.py
nwastdlib/f.py
nwastdlib/logging.py
nwastdlib/py.typed
nwastdlib/settings.py
nwastdlib/url.py
nwastdlib/version.py
nwastdlib/vlans.py
nwastdlib/graphql/__init__.py
nwastdlib/graphql/extensions/__init__.py
nwastdlib/graphql/extensions/deprecation_checker_extension.py
nwastdlib/graphql/extensions/error_handler_extension.py
nwa_stdlib-1.10.2.dist-info/licenses/LICENSE
nwa_stdlib-1.10.2.dist-info/WHEEL
nwa_stdlib-1.10.2.dist-info/METADATA
nwa_stdlib-1.10.2.dist-info/RECORD
