Metadata-Version: 2.4
Name: nwa-stdlib
Version: 1.10.2
Summary: The NWA-stdlib module.
Home-page: https://github.com/workfloworchestrator/nwa-stdlib
Author: SURF
Author-email: automation-beheer@surf.nl
Requires-Python: >=3.11,<3.14
Classifier: Intended Audience :: Information Technology
Classifier: Intended Audience :: System Administrators
Classifier: Operating System :: OS Independent
Classifier: Programming Language :: Python :: 3
Classifier: Programming Language :: Python
Classifier: Topic :: Internet
Classifier: Topic :: Software Development :: Libraries :: Python Modules
Classifier: Topic :: Software Development :: Libraries
Classifier: Topic :: Software Development
Classifier: Typing :: Typed
Classifier: Development Status :: 3 - Alpha
Classifier: Environment :: Web Environment
Classifier: Intended Audience :: Developers
Classifier: Intended Audience :: Telecommunications Industry
Classifier: License :: OSI Approved :: Apache Software License
Classifier: Programming Language :: Python :: 3 :: Only
Classifier: Programming Language :: Python :: 3.13
Classifier: Programming Language :: Python :: 3.12
Classifier: Programming Language :: Python :: 3.11
License-File: LICENSE
Requires-Dist: anyio>=3.7.0
Requires-Dist: colorama~=0.4.3
Requires-Dist: pydantic>=2.4.0
Requires-Dist: pydantic_settings
Requires-Dist: strawberry-graphql>=0.246.2
Requires-Dist: redis>=5.0, <6.0
Requires-Dist: structlog>=22.1.0
Requires-Dist: bumpversion ; extra == "dev"
Requires-Dist: jsonschema ; extra == "dev"
Requires-Dist: pre-commit ; extra == "dev"
Requires-Dist: types-redis ; extra == "dev"
Requires-Dist: anyio ; extra == "test"
Requires-Dist: apache-license-check ; extra == "test"
Requires-Dist: black ; extra == "test"
Requires-Dist: fakeredis ; extra == "test"
Requires-Dist: fastapi ; extra == "test"
Requires-Dist: httpx ; extra == "test"
Requires-Dist: mypy ; extra == "test"
Requires-Dist: mypy_extensions ; extra == "test"
Requires-Dist: pytest ; extra == "test"
Requires-Dist: pytest-cov ; extra == "test"
Requires-Dist: pytest-asyncio ; extra == "test"
Requires-Dist: redis ; extra == "test"
Requires-Dist: ruff ; extra == "test"
Project-URL: Documentation, https://workfloworchestrator.org/
Provides-Extra: dev
Provides-Extra: test
